java_to_python_transpiler/__init__.py
java_to_python_transpiler/java_to_python.py
java_to_python_transpiler/test_java_to_python.py
java_to_python_transpiler/transpile_methods.py
java_to_python_transpiler-0.1.8.dist-info/LICENSE
java_to_python_transpiler-0.1.8.dist-info/METADATA
java_to_python_transpiler-0.1.8.dist-info/WHEEL
java_to_python_transpiler-0.1.8.dist-info/RECORD
