Metadata-Version: 2.1
Name: java-to-python-transpiler
Version: 0.1.8
Summary: Transpiles Java source code into Python source code
License: MIT
Author: Hunter G.
Requires-Python: >=3.10,<4.0
Classifier: License :: OSI Approved :: MIT License
Classifier: Programming Language :: Python :: 3
Classifier: Programming Language :: Python :: 3.10
Classifier: Programming Language :: Python :: 3.11
Classifier: Programming Language :: Python :: 3.12
Requires-Dist: autopep8 (>=2.3.1,<3.0.0)
